clipthread/__init__.py
clipthread/server/config.py
clipthread/server/feign.py
clipthread/server/main.py
clipthread/server/api/__init__.py
clipthread/server/api/clipboard.py
clipthread/server/api/journal.py
clipthread_server-0.0.2.dist-info/METADATA
clipthread_server-0.0.2.dist-info/WHEEL
clipthread_server-0.0.2.dist-info/entry_points.txt
clipthread_server-0.0.2.dist-info/licenses/LICENSE
clipthread_server-0.0.2.dist-info/RECORD
